trytond/modules/currency_rate_import_ecb/README.rst
trytond/modules/currency_rate_import_ecb/__init__.py
trytond/modules/currency_rate_import_ecb/configuration.py
trytond/modules/currency_rate_import_ecb/configuration.xml
trytond/modules/currency_rate_import_ecb/cron.py
trytond/modules/currency_rate_import_ecb/cronjob.xml
trytond/modules/currency_rate_import_ecb/currency.py
trytond/modules/currency_rate_import_ecb/currency.xml
trytond/modules/currency_rate_import_ecb/icon.xml
trytond/modules/currency_rate_import_ecb/tryton.cfg
trytond/modules/currency_rate_import_ecb/versiondep.txt
trytond/modules/currency_rate_import_ecb/wizard.py
trytond/modules/currency_rate_import_ecb/wizard.xml
trytond/modules/currency_rate_import_ecb/icon/settings.svg
trytond/modules/currency_rate_import_ecb/locale/de.po
trytond/modules/currency_rate_import_ecb/locale/en.po
trytond/modules/currency_rate_import_ecb/tests/__init__.py
trytond/modules/currency_rate_import_ecb/tests/test_currency.py
trytond/modules/currency_rate_import_ecb/view/config_form.xml
trytond/modules/currency_rate_import_ecb/view/currency_form.xml
trytond/modules/currency_rate_import_ecb/view/currency_tree.xml
mds_currency_rate_import_ecb-5.4.1.dist-info/METADATA
mds_currency_rate_import_ecb-5.4.1.dist-info/WHEEL
mds_currency_rate_import_ecb-5.4.1.dist-info/entry_points.txt
mds_currency_rate_import_ecb-5.4.1.dist-info/top_level.txt
mds_currency_rate_import_ecb-5.4.1.dist-info/RECORD
